resr/__init__.py
resr/file_io.py
resr/img_util.py
resr/tiling/__init__.py
resr/tiling/process_tile.py
resr/tiling/tile_blender.py
resr/tiling/tiler.py
resr-1.0.0.dist-info/METADATA
resr-1.0.0.dist-info/WHEEL
resr-1.0.0.dist-info/RECORD
