Metadata-Version: 2.4
Name: resr
Version: 1.0.0
License-Expression: MIT
Requires-Python: >=3.10
Requires-Dist: opencv-python>=4.11.0.86
Requires-Dist: torch
Requires-Dist: torchvision
Provides-Extra: cu118
Requires-Dist: torch>=2.6.0; extra == 'cu118'
Requires-Dist: torchvision>=0.21.0; extra == 'cu118'
Provides-Extra: cu124
Requires-Dist: torch>=2.6.0; extra == 'cu124'
Requires-Dist: torchvision>=0.21.0; extra == 'cu124'
Provides-Extra: cu126
Requires-Dist: torch>=2.6.0; extra == 'cu126'
Requires-Dist: torchvision>=0.21.0; extra == 'cu126'
Provides-Extra: cu128
Requires-Dist: torch>=2.7.0; extra == 'cu128'
Requires-Dist: torchvision>=0.22.0; extra == 'cu128'
